Metadata-Version: 2.1
Name: nmtf
Version: 1.0.83
Summary: UNKNOWN
Home-page: https://github.com/paulfogel/NMTF
Author: Paul Fogel
Author-email: paul_fogel@hotmail.com
License: UNKNOWN
Platform: UNKNOWN
Classifier: Programming Language :: Python :: 3
Classifier: License :: OSI Approved :: GNU General Public License v3 (GPLv3)
Classifier: Operating System :: OS Independent
Classifier: Development Status :: 5 - Production/Stable
Requires-Python: >=3.6
Provides-Extra: apt
Provides-Extra: all
